{
  "v": 1,
  "exportedAt": 1778136021233,
  "keys": [
    "jiyiqi-practice-attempts-v1",
    "jiyiqi-practice-user-answers-v1"
  ],
  "items": {
    "jiyiqi-practice-attempts-v1": "{\"quiz|comprehensive||comp-1|\":[{\"id\":\"seed-comp-1-1\",\"bundleKey\":\"quiz|comprehensive||comp-1|\",\"ts\":1778136021226,\"title\":\"综合题1\",\"total\":75,\"correct\":45,\"percent\":60,\"choices\":{\"0\":\"D\",\"1\":\"A\",\"2\":\"A\",\"3\":\"D\",\"4\":\"C\",\"5\":\"B\",\"6\":\"C\",\"7\":\"A\",\"8\":\"B\",\"9\":\"A\",\"10\":\"D\",\"11\":\"D\",\"12\":\"B\",\"13\":\"B\",\"14\":\"B\",\"15\":\"B\",\"16\":\"B\",\"17\":\"D\",\"18\":\"A\",\"19\":\"C\",\"20\":\"D\",\"21\":\"D\",\"22\":\"A\",\"23\":\"A\",\"24\":\"D\",\"25\":\"D\",\"26\":\"C\",\"27\":\"C\",\"28\":\"D\",\"29\":\"D\",\"30\":\"D\",\"31\":\"A\",\"32\":\"D\",\"33\":\"C\",\"34\":\"D\",\"35\":\"D\",\"36\":\"A\",\"37\":\"D\",\"38\":\"C\",\"39\":\"D\",\"40\":\"A\",\"41\":\"B\",\"42\":\"D\",\"43\":\"D\",\"44\":\"A\",\"45\":\"C\",\"46\":\"B\",\"47\":\"C\",\"48\":\"A\",\"49\":\"D\",\"50\":\"B\",\"51\":\"D\",\"52\":\"A\",\"53\":\"A\",\"54\":\"C\",\"55\":\"D\",\"56\":\"C\",\"57\":\"D\",\"58\":\"D\",\"59\":\"A\",\"60\":\"C\",\"61\":\"C\",\"62\":\"D\",\"63\":\"A\",\"64\":\"C\",\"65\":\"D\",\"66\":\"D\",\"67\":\"A\",\"68\":\"B\",\"69\":\"B\",\"70\":\"B\",\"71\":\"B\",\"72\":\"C\",\"73\":\"C\",\"74\":\"C\"},\"answerMap\":{\"0\":\"D\",\"1\":\"A\",\"2\":\"A\",\"3\":\"D\",\"4\":\"B\",\"5\":\"B\",\"6\":\"D\",\"7\":\"D\",\"8\":\"A\",\"9\":\"A\",\"10\":\"D\",\"11\":\"D\",\"12\":\"B\",\"13\":\"B\",\"14\":\"B\",\"15\":\"D\",\"16\":\"C\",\"17\":\"D\",\"18\":\"C\",\"19\":\"C\",\"20\":\"D\",\"21\":\"A\",\"22\":\"A\",\"23\":\"A\",\"24\":\"D\",\"25\":\"A\",\"26\":\"C\",\"27\":\"B\",\"28\":\"D\",\"29\":\"D\",\"30\":\"D\",\"31\":\"B\",\"32\":\"B\",\"33\":\"D\",\"34\":\"D\",\"35\":\"D\",\"36\":\"A\",\"37\":\"D\",\"38\":\"C\",\"39\":\"C\",\"40\":\"A\",\"41\":\"A\",\"42\":\"D\",\"43\":\"D\",\"44\":\"A\",\"45\":\"D\",\"46\":\"D\",\"47\":\"D\",\"48\":\"A\",\"49\":\"A\",\"50\":\"C\",\"51\":\"C\",\"52\":\"A\",\"53\":\"A\",\"54\":\"C\",\"55\":\"D\",\"56\":\"D\",\"57\":\"D\",\"58\":\"B\",\"59\":\"A\",\"60\":\"D\",\"61\":\"C\",\"62\":\"C\",\"63\":\"A\",\"64\":\"D\",\"65\":\"D\",\"66\":\"D\",\"67\":\"A\",\"68\":\"C\",\"69\":\"B\",\"70\":\"B\",\"71\":\"B\",\"72\":\"A\",\"73\":\"A\",\"74\":\"A\"},\"wrongOriginIndices\":[4,6,7,8,15,16,18,21,25,27,31,32,33,39,41,45,46,47,49,50,51,56,58,60,62,64,68,72,73,74],\"practiceLayer\":\"comprehensive\",\"activeComprehensiveId\":\"comp-1\",\"activeMockId\":\"\",\"activeDomainId\":\"\"}],\"quiz|comprehensive||comp-2|\":[{\"id\":\"seed-comp-2-1\",\"bundleKey\":\"quiz|comprehensive||comp-2|\",\"ts\":1778136021228,\"title\":\"综合题2\",\"total\":75,\"correct\":50,\"percent\":67,\"choices\":{\"0\":\"A\",\"1\":\"D\",\"2\":\"D\",\"3\":\"B\",\"4\":\"C\",\"5\":\"B\",\"6\":\"B\",\"7\":\"D\",\"8\":\"D\",\"9\":\"D\",\"10\":\"A\",\"11\":\"C\",\"12\":\"A\",\"13\":\"A\",\"14\":\"C\",\"15\":\"B\",\"16\":\"B\",\"17\":\"D\",\"18\":\"B\",\"19\":\"D\",\"20\":\"B\",\"21\":\"B\",\"22\":\"A\",\"23\":\"D\",\"24\":\"A\",\"25\":\"A\",\"26\":\"C\",\"27\":\"C\",\"28\":\"B\",\"29\":\"C\",\"30\":\"C\",\"31\":\"C\",\"32\":\"A\",\"33\":\"C\",\"34\":\"A\",\"35\":\"C\",\"36\":\"C\",\"37\":\"B\",\"38\":\"C\",\"39\":\"C\",\"40\":\"B\",\"41\":\"D\",\"42\":\"D\",\"43\":\"C\",\"44\":\"B\",\"45\":\"B\",\"46\":\"D\",\"47\":\"C\",\"48\":\"B\",\"49\":\"C\",\"50\":\"A\",\"51\":\"D\",\"52\":\"B\",\"53\":\"B\",\"54\":\"B\",\"55\":\"D\",\"56\":\"D\",\"57\":\"D\",\"58\":\"D\",\"59\":\"D\",\"60\":\"A\",\"61\":\"C\",\"62\":\"C\",\"63\":\"B\",\"64\":\"B\",\"65\":\"A\",\"66\":\"D\",\"67\":\"B\",\"68\":\"A\",\"69\":\"A\",\"70\":\"A\",\"71\":\"B\",\"72\":\"D\",\"73\":\"A\",\"74\":\"B\"},\"answerMap\":{\"0\":\"C\",\"1\":\"D\",\"2\":\"D\",\"3\":\"B\",\"4\":\"C\",\"5\":\"D\",\"6\":\"D\",\"7\":\"D\",\"8\":\"D\",\"9\":\"D\",\"10\":\"B\",\"11\":\"C\",\"12\":\"B\",\"13\":\"B\",\"14\":\"B\",\"15\":\"D\",\"16\":\"B\",\"17\":\"D\",\"18\":\"B\",\"19\":\"C\",\"20\":\"B\",\"21\":\"B\",\"22\":\"A\",\"23\":\"D\",\"24\":\"A\",\"25\":\"D\",\"26\":\"C\",\"27\":\"C\",\"28\":\"A\",\"29\":\"C\",\"30\":\"C\",\"31\":\"B\",\"32\":\"A\",\"33\":\"C\",\"34\":\"A\",\"35\":\"C\",\"36\":\"A\",\"37\":\"B\",\"38\":\"C\",\"39\":\"B\",\"40\":\"B\",\"41\":\"D\",\"42\":\"C\",\"43\":\"C\",\"44\":\"A\",\"45\":\"B\",\"46\":\"D\",\"47\":\"D\",\"48\":\"C\",\"49\":\"C\",\"50\":\"A\",\"51\":\"D\",\"52\":\"A\",\"53\":\"B\",\"54\":\"D\",\"55\":\"D\",\"56\":\"D\",\"57\":\"B\",\"58\":\"D\",\"59\":\"D\",\"60\":\"D\",\"61\":\"C\",\"62\":\"C\",\"63\":\"B\",\"64\":\"B\",\"65\":\"A\",\"66\":\"D\",\"67\":\"A\",\"68\":\"A\",\"69\":\"A\",\"70\":\"A\",\"71\":\"B\",\"72\":\"C\",\"73\":\"D\",\"74\":\"B\"},\"wrongOriginIndices\":[0,5,6,10,12,13,14,15,19,25,28,31,36,39,42,44,47,48,52,54,57,60,67,72,73],\"practiceLayer\":\"comprehensive\",\"activeComprehensiveId\":\"comp-2\",\"activeMockId\":\"\",\"activeDomainId\":\"\"}],\"quiz|comprehensive||comp-3|\":[{\"id\":\"seed-comp-3-1\",\"bundleKey\":\"quiz|comprehensive||comp-3|\",\"ts\":1778136021229,\"title\":\"综合题3\",\"total\":75,\"correct\":48,\"percent\":64,\"choices\":{\"0\":\"C\",\"1\":\"B\",\"2\":\"B\",\"3\":\"A\",\"4\":\"B\",\"5\":\"D\",\"6\":\"D\",\"7\":\"C\",\"8\":\"A\",\"9\":\"D\",\"10\":\"C\",\"11\":\"A\",\"12\":\"C\",\"13\":\"A\",\"14\":\"B\",\"15\":\"B\",\"16\":\"B\",\"17\":\"C\",\"18\":\"D\",\"19\":\"B\",\"20\":\"B\",\"21\":\"A\",\"22\":\"C\",\"23\":\"D\",\"24\":\"C\",\"25\":\"C\",\"26\":\"A\",\"27\":\"C\",\"28\":\"D\",\"29\":\"B\",\"30\":\"D\",\"31\":\"D\",\"32\":\"B\",\"33\":\"D\",\"34\":\"A\",\"35\":\"B\",\"36\":\"C\",\"37\":\"C\",\"38\":\"D\",\"39\":\"D\",\"40\":\"A\",\"41\":\"C\",\"42\":\"A\",\"43\":\"A\",\"44\":\"D\",\"45\":\"C\",\"46\":\"D\",\"47\":\"B\",\"48\":\"C\",\"49\":\"D\",\"50\":\"C\",\"51\":\"C\",\"52\":\"B\",\"53\":\"A\",\"54\":\"C\",\"55\":\"C\",\"56\":\"A\",\"57\":\"C\",\"58\":\"B\",\"59\":\"D\",\"60\":\"A\",\"61\":\"B\",\"62\":\"C\",\"63\":\"B\",\"64\":\"D\",\"65\":\"A\",\"66\":\"A\",\"67\":\"C\",\"68\":\"A\",\"69\":\"A\",\"70\":\"A\",\"71\":\"C\",\"72\":\"D\",\"73\":\"A\",\"74\":\"A\"},\"answerMap\":{\"0\":\"C\",\"1\":\"B\",\"2\":\"C\",\"3\":\"A\",\"4\":\"B\",\"5\":\"D\",\"6\":\"B\",\"7\":\"C\",\"8\":\"D\",\"9\":\"D\",\"10\":\"C\",\"11\":\"B\",\"12\":\"C\",\"13\":\"A\",\"14\":\"B\",\"15\":\"B\",\"16\":\"B\",\"17\":\"C\",\"18\":\"C\",\"19\":\"D\",\"20\":\"B\",\"21\":\"A\",\"22\":\"C\",\"23\":\"C\",\"24\":\"C\",\"25\":\"C\",\"26\":\"B\",\"27\":\"C\",\"28\":\"D\",\"29\":\"B\",\"30\":\"C\",\"31\":\"C\",\"32\":\"B\",\"33\":\"A\",\"34\":\"A\",\"35\":\"C\",\"36\":\"C\",\"37\":\"C\",\"38\":\"B\",\"39\":\"D\",\"40\":\"A\",\"41\":\"D\",\"42\":\"A\",\"43\":\"D\",\"44\":\"C\",\"45\":\"B\",\"46\":\"B\",\"47\":\"B\",\"48\":\"C\",\"49\":\"B\",\"50\":\"C\",\"51\":\"C\",\"52\":\"B\",\"53\":\"A\",\"54\":\"C\",\"55\":\"C\",\"56\":\"C\",\"57\":\"C\",\"58\":\"B\",\"59\":\"D\",\"60\":\"A\",\"61\":\"B\",\"62\":\"B\",\"63\":\"B\",\"64\":\"D\",\"65\":\"A\",\"66\":\"C\",\"67\":\"C\",\"68\":\"D\",\"69\":\"B\",\"70\":\"D\",\"71\":\"C\",\"72\":\"C\",\"73\":\"A\",\"74\":\"D\"},\"wrongOriginIndices\":[2,6,8,11,18,19,23,26,30,31,33,35,38,41,43,44,45,46,49,56,62,66,68,69,70,72,74],\"practiceLayer\":\"comprehensive\",\"activeComprehensiveId\":\"comp-3\",\"activeMockId\":\"\",\"activeDomainId\":\"\"}],\"quiz|comprehensive||comp-4|\":[{\"id\":\"seed-comp-4-1\",\"bundleKey\":\"quiz|comprehensive||comp-4|\",\"ts\":1778136021231,\"title\":\"综合题4\",\"total\":74,\"correct\":49,\"percent\":66,\"choices\":{\"0\":\"B\",\"1\":\"D\",\"2\":\"B\",\"3\":\"B\",\"4\":\"C\",\"5\":\"B\",\"6\":\"B\",\"7\":\"A\",\"8\":\"C\",\"9\":\"B\",\"10\":\"A\",\"11\":\"C\",\"12\":\"D\",\"13\":\"B\",\"14\":\"A\",\"15\":\"D\",\"16\":\"B\",\"17\":\"A\",\"18\":\"A\",\"19\":\"C\",\"20\":\"D\",\"21\":\"A\",\"22\":\"B\",\"23\":\"A\",\"24\":\"C\",\"25\":\"D\",\"26\":\"C\",\"27\":\"A\",\"28\":\"B\",\"29\":\"C\",\"30\":\"B\",\"31\":\"B\",\"32\":\"C\",\"33\":\"D\",\"34\":\"A\",\"35\":\"B\",\"36\":\"C\",\"37\":\"D\",\"38\":\"A\",\"39\":\"C\",\"40\":\"B\",\"41\":\"A\",\"42\":\"A\",\"43\":\"C\",\"44\":\"B\",\"45\":\"A\",\"46\":\"D\",\"47\":\"A\",\"48\":\"D\",\"49\":\"A\",\"50\":\"C\",\"51\":\"D\",\"52\":\"B\",\"53\":\"D\",\"54\":\"C\",\"55\":\"A\",\"56\":\"C\",\"57\":\"C\",\"58\":\"B\",\"59\":\"B\",\"60\":\"B\",\"61\":\"B\",\"62\":\"D\",\"63\":\"B\",\"64\":\"D\",\"65\":\"C\",\"66\":\"C\",\"67\":\"B\",\"68\":\"B\",\"69\":\"C\",\"70\":\"D\",\"71\":\"C\",\"72\":\"D\",\"73\":\"B\"},\"answerMap\":{\"0\":\"B\",\"1\":\"A\",\"2\":\"D\",\"3\":\"A\",\"4\":\"C\",\"5\":\"D\",\"6\":\"A\",\"7\":\"C\",\"8\":\"C\",\"9\":\"B\",\"10\":\"A\",\"11\":\"B\",\"12\":\"D\",\"13\":\"D\",\"14\":\"A\",\"15\":\"A\",\"16\":\"B\",\"17\":\"A\",\"18\":\"D\",\"19\":\"C\",\"20\":\"D\",\"21\":\"A\",\"22\":\"A\",\"23\":\"B\",\"24\":\"D\",\"25\":\"D\",\"26\":\"C\",\"27\":\"A\",\"28\":\"B\",\"29\":\"C\",\"30\":\"B\",\"31\":\"C\",\"32\":\"D\",\"33\":\"D\",\"34\":\"A\",\"35\":\"D\",\"36\":\"A\",\"37\":\"D\",\"38\":\"A\",\"39\":\"C\",\"40\":\"B\",\"41\":\"B\",\"42\":\"A\",\"43\":\"A\",\"44\":\"B\",\"45\":\"A\",\"46\":\"D\",\"47\":\"A\",\"48\":\"D\",\"49\":\"C\",\"50\":\"C\",\"51\":\"D\",\"52\":\"B\",\"53\":\"D\",\"54\":\"B\",\"55\":\"C\",\"56\":\"C\",\"57\":\"C\",\"58\":\"B\",\"59\":\"B\",\"60\":\"B\",\"61\":\"C\",\"62\":\"D\",\"63\":\"B\",\"64\":\"D\",\"65\":\"A\",\"66\":\"C\",\"67\":\"B\",\"68\":\"B\",\"69\":\"C\",\"70\":\"D\",\"71\":\"C\",\"72\":\"A\",\"73\":\"B\"},\"wrongOriginIndices\":[1,2,3,5,6,7,11,13,15,18,22,23,24,31,32,35,36,41,43,49,54,55,61,65,72],\"practiceLayer\":\"comprehensive\",\"activeComprehensiveId\":\"comp-4\",\"activeMockId\":\"\",\"activeDomainId\":\"\"}],\"quiz|mock|||mock-1\":[{\"id\":\"seed-mock-1-1\",\"bundleKey\":\"quiz|mock|||mock-1\",\"ts\":1778136021233,\"title\":\"模拟题1\",\"total\":75,\"correct\":75,\"percent\":100,\"choices\":{\"0\":\"A\",\"1\":\"A\",\"2\":\"A\",\"3\":\"C\",\"4\":\"D\",\"5\":\"B\",\"6\":\"C\",\"7\":\"D\",\"8\":\"D\",\"9\":\"C\",\"10\":\"A\",\"11\":\"D\",\"12\":\"C\",\"13\":\"B\",\"14\":\"B\",\"15\":\"B\",\"16\":\"D\",\"17\":\"B\",\"18\":\"C\",\"19\":\"C\",\"20\":\"B\",\"21\":\"A\",\"22\":\"C\",\"23\":\"D\",\"24\":\"C\",\"25\":\"B\",\"26\":\"B\",\"27\":\"C\",\"28\":\"B\",\"29\":\"B\",\"30\":\"D\",\"31\":\"C\",\"32\":\"A\",\"33\":\"C\",\"34\":\"C\",\"35\":\"B\",\"36\":\"A\",\"37\":\"C\",\"38\":\"D\",\"39\":\"D\",\"40\":\"C\",\"41\":\"D\",\"42\":\"C\",\"43\":\"B\",\"44\":\"A\",\"45\":\"D\",\"46\":\"A\",\"47\":\"B\",\"48\":\"C\",\"49\":\"C\",\"50\":\"A\",\"51\":\"A\",\"52\":\"B\",\"53\":\"A\",\"54\":\"A\",\"55\":\"A\",\"56\":\"A\",\"57\":\"D\",\"58\":\"A\",\"59\":\"C\",\"60\":\"D\",\"61\":\"B\",\"62\":\"B\",\"63\":\"A\",\"64\":\"B\",\"65\":\"B\",\"66\":\"B\",\"67\":\"B\",\"68\":\"D\",\"69\":\"B\",\"70\":\"D\",\"71\":\"C\",\"72\":\"C\",\"73\":\"A\",\"74\":\"A\"},\"answerMap\":{\"0\":\"A\",\"1\":\"A\",\"2\":\"A\",\"3\":\"C\",\"4\":\"D\",\"5\":\"B\",\"6\":\"C\",\"7\":\"D\",\"8\":\"D\",\"9\":\"C\",\"10\":\"A\",\"11\":\"D\",\"12\":\"C\",\"13\":\"B\",\"14\":\"B\",\"15\":\"B\",\"16\":\"D\",\"17\":\"B\",\"18\":\"C\",\"19\":\"C\",\"20\":\"B\",\"21\":\"A\",\"22\":\"C\",\"23\":\"D\",\"24\":\"C\",\"25\":\"B\",\"26\":\"B\",\"27\":\"C\",\"28\":\"B\",\"29\":\"B\",\"30\":\"D\",\"31\":\"C\",\"32\":\"A\",\"33\":\"C\",\"34\":\"C\",\"35\":\"B\",\"36\":\"A\",\"37\":\"C\",\"38\":\"D\",\"39\":\"D\",\"40\":\"C\",\"41\":\"D\",\"42\":\"C\",\"43\":\"B\",\"44\":\"A\",\"45\":\"D\",\"46\":\"A\",\"47\":\"B\",\"48\":\"C\",\"49\":\"C\",\"50\":\"A\",\"51\":\"A\",\"52\":\"B\",\"53\":\"A\",\"54\":\"A\",\"55\":\"A\",\"56\":\"A\",\"57\":\"D\",\"58\":\"A\",\"59\":\"C\",\"60\":\"D\",\"61\":\"B\",\"62\":\"B\",\"63\":\"A\",\"64\":\"B\",\"65\":\"B\",\"66\":\"B\",\"67\":\"B\",\"68\":\"D\",\"69\":\"B\",\"70\":\"D\",\"71\":\"C\",\"72\":\"C\",\"73\":\"A\",\"74\":\"A\"},\"wrongOriginIndices\":[],\"practiceLayer\":\"mock\",\"activeComprehensiveId\":\"\",\"activeMockId\":\"mock-1\",\"activeDomainId\":\"\"}]}",
    "jiyiqi-practice-user-answers-v1": "{\"v\":1,\"bySetKey\":{\"zonghe_1\":{\"0\":\"D\",\"1\":\"A\",\"2\":\"A\",\"3\":\"D\",\"4\":\"C\",\"5\":\"B\",\"6\":\"C\",\"7\":\"A\",\"8\":\"B\",\"9\":\"A\",\"10\":\"D\",\"11\":\"D\",\"12\":\"B\",\"13\":\"B\",\"14\":\"B\",\"15\":\"B\",\"16\":\"B\",\"17\":\"D\",\"18\":\"A\",\"19\":\"C\",\"20\":\"D\",\"21\":\"D\",\"22\":\"A\",\"23\":\"A\",\"24\":\"D\",\"25\":\"D\",\"26\":\"C\",\"27\":\"C\",\"28\":\"D\",\"29\":\"D\",\"30\":\"D\",\"31\":\"A\",\"32\":\"D\",\"33\":\"C\",\"34\":\"D\",\"35\":\"D\",\"36\":\"A\",\"37\":\"D\",\"38\":\"C\",\"39\":\"D\",\"40\":\"A\",\"41\":\"B\",\"42\":\"D\",\"43\":\"D\",\"44\":\"A\",\"45\":\"C\",\"46\":\"B\",\"47\":\"C\",\"48\":\"A\",\"49\":\"D\",\"50\":\"B\",\"51\":\"D\",\"52\":\"A\",\"53\":\"A\",\"54\":\"C\",\"55\":\"D\",\"56\":\"C\",\"57\":\"D\",\"58\":\"D\",\"59\":\"A\",\"60\":\"C\",\"61\":\"C\",\"62\":\"D\",\"63\":\"A\",\"64\":\"C\",\"65\":\"D\",\"66\":\"D\",\"67\":\"A\",\"68\":\"B\",\"69\":\"B\",\"70\":\"B\",\"71\":\"B\",\"72\":\"C\",\"73\":\"C\",\"74\":\"C\"},\"zonghe_2\":{\"0\":\"A\",\"1\":\"D\",\"2\":\"D\",\"3\":\"B\",\"4\":\"C\",\"5\":\"B\",\"6\":\"B\",\"7\":\"D\",\"8\":\"D\",\"9\":\"D\",\"10\":\"A\",\"11\":\"C\",\"12\":\"A\",\"13\":\"A\",\"14\":\"C\",\"15\":\"B\",\"16\":\"B\",\"17\":\"D\",\"18\":\"B\",\"19\":\"D\",\"20\":\"B\",\"21\":\"B\",\"22\":\"A\",\"23\":\"D\",\"24\":\"A\",\"25\":\"A\",\"26\":\"C\",\"27\":\"C\",\"28\":\"B\",\"29\":\"C\",\"30\":\"C\",\"31\":\"C\",\"32\":\"A\",\"33\":\"C\",\"34\":\"A\",\"35\":\"C\",\"36\":\"C\",\"37\":\"B\",\"38\":\"C\",\"39\":\"C\",\"40\":\"B\",\"41\":\"D\",\"42\":\"D\",\"43\":\"C\",\"44\":\"B\",\"45\":\"B\",\"46\":\"D\",\"47\":\"C\",\"48\":\"B\",\"49\":\"C\",\"50\":\"A\",\"51\":\"D\",\"52\":\"B\",\"53\":\"B\",\"54\":\"B\",\"55\":\"D\",\"56\":\"D\",\"57\":\"D\",\"58\":\"D\",\"59\":\"D\",\"60\":\"A\",\"61\":\"C\",\"62\":\"C\",\"63\":\"B\",\"64\":\"B\",\"65\":\"A\",\"66\":\"D\",\"67\":\"B\",\"68\":\"A\",\"69\":\"A\",\"70\":\"A\",\"71\":\"B\",\"72\":\"D\",\"73\":\"A\",\"74\":\"B\"},\"zonghe_3\":{\"0\":\"C\",\"1\":\"B\",\"2\":\"B\",\"3\":\"A\",\"4\":\"B\",\"5\":\"D\",\"6\":\"D\",\"7\":\"C\",\"8\":\"A\",\"9\":\"D\",\"10\":\"C\",\"11\":\"A\",\"12\":\"C\",\"13\":\"A\",\"14\":\"B\",\"15\":\"B\",\"16\":\"B\",\"17\":\"C\",\"18\":\"D\",\"19\":\"B\",\"20\":\"B\",\"21\":\"A\",\"22\":\"C\",\"23\":\"D\",\"24\":\"C\",\"25\":\"C\",\"26\":\"A\",\"27\":\"C\",\"28\":\"D\",\"29\":\"B\",\"30\":\"D\",\"31\":\"D\",\"32\":\"B\",\"33\":\"D\",\"34\":\"A\",\"35\":\"B\",\"36\":\"C\",\"37\":\"C\",\"38\":\"D\",\"39\":\"D\",\"40\":\"A\",\"41\":\"C\",\"42\":\"A\",\"43\":\"A\",\"44\":\"D\",\"45\":\"C\",\"46\":\"D\",\"47\":\"B\",\"48\":\"C\",\"49\":\"D\",\"50\":\"C\",\"51\":\"C\",\"52\":\"B\",\"53\":\"A\",\"54\":\"C\",\"55\":\"C\",\"56\":\"A\",\"57\":\"C\",\"58\":\"B\",\"59\":\"D\",\"60\":\"A\",\"61\":\"B\",\"62\":\"C\",\"63\":\"B\",\"64\":\"D\",\"65\":\"A\",\"66\":\"A\",\"67\":\"C\",\"68\":\"A\",\"69\":\"A\",\"70\":\"A\",\"71\":\"C\",\"72\":\"D\",\"73\":\"A\",\"74\":\"A\"},\"zonghe_4\":{\"0\":\"B\",\"1\":\"D\",\"2\":\"B\",\"3\":\"B\",\"4\":\"C\",\"5\":\"B\",\"6\":\"B\",\"7\":\"A\",\"8\":\"C\",\"9\":\"B\",\"10\":\"A\",\"11\":\"C\",\"12\":\"D\",\"13\":\"B\",\"14\":\"A\",\"15\":\"D\",\"16\":\"B\",\"17\":\"A\",\"18\":\"A\",\"19\":\"C\",\"20\":\"D\",\"21\":\"A\",\"22\":\"B\",\"23\":\"A\",\"24\":\"C\",\"25\":\"D\",\"26\":\"C\",\"27\":\"A\",\"28\":\"B\",\"29\":\"C\",\"30\":\"B\",\"31\":\"B\",\"32\":\"C\",\"33\":\"D\",\"34\":\"A\",\"35\":\"B\",\"36\":\"C\",\"37\":\"D\",\"38\":\"A\",\"39\":\"C\",\"40\":\"B\",\"41\":\"A\",\"42\":\"A\",\"43\":\"C\",\"44\":\"B\",\"45\":\"A\",\"46\":\"D\",\"47\":\"A\",\"48\":\"D\",\"49\":\"A\",\"50\":\"C\",\"51\":\"D\",\"52\":\"B\",\"53\":\"D\",\"54\":\"C\",\"55\":\"A\",\"56\":\"C\",\"57\":\"C\",\"58\":\"B\",\"59\":\"B\",\"60\":\"B\",\"61\":\"B\",\"62\":\"D\",\"63\":\"B\",\"64\":\"D\",\"65\":\"C\",\"66\":\"C\",\"67\":\"B\",\"68\":\"B\",\"69\":\"C\",\"70\":\"D\",\"71\":\"C\",\"72\":\"D\",\"73\":\"B\"},\"moni_1\":{\"0\":\"A\",\"1\":\"A\",\"2\":\"A\",\"3\":\"C\",\"4\":\"D\",\"5\":\"B\",\"6\":\"C\",\"7\":\"D\",\"8\":\"D\",\"9\":\"C\",\"10\":\"A\",\"11\":\"D\",\"12\":\"C\",\"13\":\"B\",\"14\":\"B\",\"15\":\"B\",\"16\":\"D\",\"17\":\"B\",\"18\":\"C\",\"19\":\"C\",\"20\":\"B\",\"21\":\"A\",\"22\":\"C\",\"23\":\"D\",\"24\":\"C\",\"25\":\"B\",\"26\":\"B\",\"27\":\"C\",\"28\":\"B\",\"29\":\"B\",\"30\":\"D\",\"31\":\"C\",\"32\":\"A\",\"33\":\"C\",\"34\":\"C\",\"35\":\"B\",\"36\":\"A\",\"37\":\"C\",\"38\":\"D\",\"39\":\"D\",\"40\":\"C\",\"41\":\"D\",\"42\":\"C\",\"43\":\"B\",\"44\":\"A\",\"45\":\"D\",\"46\":\"A\",\"47\":\"B\",\"48\":\"C\",\"49\":\"C\",\"50\":\"A\",\"51\":\"A\",\"52\":\"B\",\"53\":\"A\",\"54\":\"A\",\"55\":\"A\",\"56\":\"A\",\"57\":\"D\",\"58\":\"A\",\"59\":\"C\",\"60\":\"D\",\"61\":\"B\",\"62\":\"B\",\"63\":\"A\",\"64\":\"B\",\"65\":\"B\",\"66\":\"B\",\"67\":\"B\",\"68\":\"D\",\"69\":\"B\",\"70\":\"D\",\"71\":\"C\",\"72\":\"C\",\"73\":\"A\",\"74\":\"A\"}},\"generatedAt\":1778136021233}"
  }
}